python_package/__init__.py
python_package/topsis.py
charul_jain99-0.0.1.dist-info/LICENSE.txt
charul_jain99-0.0.1.dist-info/METADATA
charul_jain99-0.0.1.dist-info/WHEEL
charul_jain99-0.0.1.dist-info/top_level.txt
charul_jain99-0.0.1.dist-info/RECORD
