Metadata-Version: 2.1
Name: charul-jain99
Version: 0.0.1
Summary: It is a self created package for TOPSIS
Home-page: UNKNOWN
Author: Example Author
Author-email: charuljain140@gmail.com
License: UNKNOWN
Platform: UNKNOWN
Classifier: Programming Language :: Python :: 3
Classifier: License :: OSI Approved :: MIT License
Classifier: Operating System :: OS Independent
Requires-Python: >=3.6
